pobject/__init__.py
pobject/file.py
pobject/pobject.py
pobject-0.1.5.dist-info/WHEEL
pobject-0.1.5.dist-info/METADATA
pobject-0.1.5.dist-info/RECORD
