Metadata-Version: 2.1
Name: pobject
Version: 0.1.5
Summary: pobject
Author: Eyal Levin
Author-email: eyalev@gmail.com
Requires-Python: >=3.6,<4.0
Classifier: Programming Language :: Python :: 3
Classifier: Programming Language :: Python :: 3.6
Classifier: Programming Language :: Python :: 3.7
Classifier: Programming Language :: Python :: 3.8
Requires-Dist: is-url (>=0.1.2,<0.2.0)
Requires-Dist: pyyaml (>=5.3.1,<6.0.0)
